outrun/__init__.py
outrun/__main__.py
outrun/args.py
outrun/config.py
outrun/constants.py
outrun/logger.py
outrun/filesystem/__init__.py
outrun/filesystem/common.py
outrun/filesystem/filesystem.py
outrun/filesystem/service.py
outrun/filesystem/caching/__init__.py
outrun/filesystem/caching/cache.py
outrun/filesystem/caching/common.py
outrun/filesystem/caching/filesystem.py
outrun/filesystem/caching/prefetching.py
outrun/filesystem/caching/service.py
outrun/filesystem/fuse/__init__.py
outrun/filesystem/fuse/fuse.py
outrun/operations/__init__.py
outrun/operations/common.py
outrun/operations/environment.py
outrun/operations/events.py
outrun/operations/local.py
outrun/operations/remote.py
outrun/rpc/__init__.py
outrun-1.1.0.dist-info/LICENSE.txt
outrun-1.1.0.dist-info/METADATA
outrun-1.1.0.dist-info/WHEEL
outrun-1.1.0.dist-info/entry_points.txt
outrun-1.1.0.dist-info/top_level.txt
outrun-1.1.0.dist-info/RECORD
