Metadata-Version: 2.1
Name: outrun
Version: 1.1.0
Summary: Delegate execution of a local command to a remote machine.
Home-page: https://github.com/Overv/outrun
Download-URL: https://github.com/Overv/outrun
Author: Alexander Overvoorde
Author-email: overv161@gmail.com
License: Apache
Classifier: Development Status :: 3 - Alpha
Classifier: Environment :: Console
Classifier: Programming Language :: Python :: 3
Classifier: Programming Language :: Python :: 3.7
Classifier: Intended Audience :: Information Technology
Classifier: License :: OSI Approved :: Apache Software License
Classifier: Operating System :: POSIX :: Linux
Classifier: Topic :: System :: Clustering
Requires-Python: >=3.7
License-File: LICENSE.txt
Requires-Dist: msgpack >=1.0.0
Requires-Dist: pyzmq >=19.0.0
Requires-Dist: lz4 >=3.0.2
Requires-Dist: fasteners >=0.15
Requires-Dist: semver >=2.9.1
Provides-Extra: dev
Requires-Dist: rope >=0.14.0 ; extra == 'dev'
Requires-Dist: flake8 >=3.7.9 ; extra == 'dev'
Requires-Dist: flake8-docstrings >=1.5.0 ; extra == 'dev'
Requires-Dist: flake8-import-order >=0.18.1 ; extra == 'dev'
Requires-Dist: black >=19.10b0 ; extra == 'dev'
Requires-Dist: pylint >=2.4.4 ; extra == 'dev'
Requires-Dist: mypy >=0.770 ; extra == 'dev'
Requires-Dist: pytest >=5.4.1 ; extra == 'dev'
Requires-Dist: pytest-cov >=2.8.1 ; extra == 'dev'
Requires-Dist: python-vagrant >=0.5.15 ; extra == 'dev'
